gemseo_java/__init__.py
gemseo_java/jep_java_discipline.py
gemseo_java/jnius_java_discipline.py
gemseo_java-1.0.0.post0.dist-info/LICENSE.txt
gemseo_java-1.0.0.post0.dist-info/METADATA
gemseo_java-1.0.0.post0.dist-info/WHEEL
gemseo_java-1.0.0.post0.dist-info/entry_points.txt
gemseo_java-1.0.0.post0.dist-info/top_level.txt
gemseo_java-1.0.0.post0.dist-info/RECORD
