Metadata-Version: 2.1
Name: gemseo-java
Version: 1.0.0.post0
Summary: Java interface for GEMSEO.
Home-page: https://www.irt-saintexupery.com
Author: François Gallard
Author-email: contact@gemseo.org
License: UNKNOWN
Platform: UNKNOWN
Classifier: Intended Audience :: Science/Research
Classifier: Topic :: Scientific/Engineering
Classifier: Operating System :: POSIX :: Linux
Classifier: Operating System :: MacOS
Classifier: Operating System :: Microsoft :: Windows
Classifier: Programming Language :: Python :: 3 :: Only
Classifier: Programming Language :: Python :: 3.6
Classifier: Programming Language :: Python :: 3.7
Classifier: Programming Language :: Python :: 3.8
Classifier: Programming Language :: Python :: 3.9
Requires-Python: <3.10,>=3.6
License-File: LICENSE.txt
Requires-Dist: gemseo (>=3.2.0)
Requires-Dist: numpy
Requires-Dist: pyjnius
Requires-Dist: jep
Provides-Extra: test
Requires-Dist: packaging (<21) ; extra == 'test'
Requires-Dist: pytest ; extra == 'test'
Requires-Dist: pytest-cov ; extra == 'test'
Requires-Dist: pytest-xdist ; extra == 'test'
